README.md
licenses.txt
setup.py
PBI_SELENIUM/Routine.py
PBI_SELENIUM/__init__.py
PBI_SELENIUM.egg-info/PKG-INFO
PBI_SELENIUM.egg-info/SOURCES.txt
PBI_SELENIUM.egg-info/dependency_links.txt
PBI_SELENIUM.egg-info/top_level.txt