Metadata-Version: 2.1
Name: PBI-SELENIUM
Version: 1.0
Summary: package for routine operations in power bi
Author: Andre Ailton
Author-email: andre.ailtonf.10@gmail.com
Keywords: Selenium,PowerBi,Automatization,automation
License-File: licenses.txt
